{
  "indexes": [
    {
      "collectionGroup": "attendance",
      "queryScope": "COLLECTION",
      "fields": [
        {
          "fieldPath": "student_id",
          "order": "ASCENDING"
        },
        {
          "fieldPath": "session_id",
          "order": "ASCENDING"
        }
      ]
    },
    {
      "collectionGroup": "attendance",
      "queryScope": "COLLECTION",
      "fields": [
        {
          "fieldPath": "student_id",
          "order": "ASCENDING"
        },
        {
          "fieldPath": "subject_id",
          "order": "ASCENDING"
        }
      ]
    },
    {
      "collectionGroup": "attendance",
      "queryScope": "COLLECTION",
      "fields": [
        {
          "fieldPath": "session_id",
          "order": "ASCENDING"
        },
        {
          "fieldPath": "status",
          "order": "ASCENDING"
        }
      ]
    },
    {
      "collectionGroup": "lecture_sessions",
      "queryScope": "COLLECTION",
      "fields": [
        {
          "fieldPath": "faculty_id",
          "order": "ASCENDING"
        },
        {
          "fieldPath": "status",
          "order": "ASCENDING"
        }
      ]
    },
    {
      "collectionGroup": "lecture_sessions",
      "queryScope": "COLLECTION",
      "fields": [
        {
          "fieldPath": "status",
          "order": "ASCENDING"
        },
        {
          "fieldPath": "qr_expires_at",
          "order": "ASCENDING"
        }
      ]
    },
    {
      "collectionGroup": "attendance_stats",
      "queryScope": "COLLECTION",
      "fields": [
        {
          "fieldPath": "student_id",
          "order": "ASCENDING"
        },
        {
          "fieldPath": "subject_id",
          "order": "ASCENDING"
        }
      ]
    }
  ],
  "fieldOverrides": []
}

